indiredis/__init__.py
indiredis/__main__.py
indiredis/indiredis/data/defaults.json
indiredis/indiredis/data/project.json
indiredis/indiredis/data/textblocks_json/en.json
indiredis/indiredis/static/css/w3-theme-ski.css
indiredis/indiredis/static/images/logo.svg
indiredis/indiredis/static/images/logo_icon16.svg
indiredis/webcode/__init__.py
indiredis/webcode/authenticate.py
indiredis/webcode/blobs.py
indiredis/webcode/devices.py
indiredis/webcode/setvalues.py
indiredis-0.7.2.dist-info/LICENSE
indiredis-0.7.2.dist-info/WHEEL
indiredis-0.7.2.dist-info/METADATA
indiredis-0.7.2.dist-info/RECORD
