Metadata-Version: 2.1
Name: indiredis
Version: 0.7.2
Summary: An INDI web client for general Instrument control. If the package is run, it provides a web service for controlling instruments. If imported, it provides functions which can be adapted to your own web server.
Keywords: indi,client,astronomy,instrument
Author-email: Bernard Czenkusz <bernie@skipole.co.uk>
Requires-Python: >=3.9
Classifier: License :: OSI Approved :: MIT License
Classifier: Operating System :: POSIX :: Linux
Classifier: Topic :: Scientific/Engineering :: Astronomy
Classifier: Topic :: Scientific/Engineering :: Interface Engine/Protocol Translator
Requires-Dist: skipole>=5.5.2
Requires-Dist: indi-mr>=0.4.0
Requires-Dist: paho-mqtt>=1.5.1
Requires-Dist: redis>=3.5.3
Requires-Dist: waitress>=1.4.4
Project-URL: Documentation, https://indiredis.readthedocs.io
Project-URL: Source, https://github.com/bernie-skipole/indi
